talonlib.py
talonlib-1.3.1b0.dist-info/licenses/LICENSE
talonlib-1.3.1b0.dist-info/METADATA
talonlib-1.3.1b0.dist-info/WHEEL
talonlib-1.3.1b0.dist-info/top_level.txt
talonlib-1.3.1b0.dist-info/RECORD
