Metadata-Version: 2.4
Name: talonlib
Version: 1.3.1b0
Summary: УНППТ™ - Уникальная Необратимая Публичная Подпись Талона
Author: Morozoff_
Classifier: Development Status :: 4 - Beta
Classifier: License :: OSI Approved :: GNU General Public License v3 (GPLv3)
Classifier: Programming Language :: Python :: 3
License-File: LICENSE
Requires-Dist: psutil
Dynamic: author
Dynamic: classifier
Dynamic: description
Dynamic: description-content-type
Dynamic: license-file
Dynamic: requires-dist
Dynamic: summary
